{
  "word": "គប់",
  "type": "kh_en",
  "definitions": [
    {
      "pos": "",
      "example": "",
      "definition_text": "to throw (something at someone)"
    },
    {
      "pos": "",
      "example": "",
      "definition_text": "to join together, to associate"
    },
    {
      "pos": "",
      "example": "",
      "definition_text": "faggot, bundle of sticks or straw used as a torch, twist of straw"
    },
    {
      "pos": "",
      "example": "",
      "definition_text": "large wooden mallet"
    }
  ],
  "synonyms": [],
  "antonyms": [],
  "similar_words": [],
  "sound": null
}
