{
  "word": "ពរ",
  "type": "kh_kh",
  "definitions": [
    {
      "pos": "",
      "example": "",
      "definition_text": "ពរពរ   សំ. បា.  ( ន. )  (វរ) គុណជាត​ដ៏​ប្រសើរ; គុណជាត​ឬ​អ្វី​ៗ ដែល​គួរ​ប្រាថ្នា, គួរ​ចង់​បាន, គួរ​ជ្រើសរើស​យក​តាម​គាប់​ចិត្ត : សូម​ពរ, ឲ្យ​ពរ, ទទួល​ពរ ។ ឲ្យ​ពរ​សព្ទ​សាធុការ បញ្ចេញ​សូរ​សព្ទ​ថា សាធុ សូម​ឲ្យ... បាន​ប្រកប​តាម​បំណង!... ។ ស្រែក​ឲ្យ​ពរ​ឲ្យ​ជ័យ ស្រែក​ឲ្យ​ពរ​ថា សូម​ឲ្យ... មាន​ជ័យ​ជម្នះ ! ដូច​យ៉ាង​ស្រែក​ថា ជយោ ! ឬ ជយោ ! ជយោ ! ជាដើម (ម. ព. នោះ​ផង) ។ ពាក្យ​នេះ សំ. បា. ប្រើ​ជា គុ. ក៏​បាន ប្រែ​ថា “ប្រសើរ; ដែល​គួរ​ប្រាថ្នា, គួរ​ចង់​បាន, គួរ​ជ្រើសរើស​យក​តាម​គាប់​ចិត្ត”; ខ្មែរ​ប្រើ​ក្លាយ​មក​ជា ព្រះ ក៏​មាន, នៅ​ជា វរ ឬ វរៈ តាម​រូប​ដើម​ក៏​មាន (ម. ព. ព្រះ និង វរ ឬ វរៈ ទៀត​ផង) ។ \n\n ( ន. )  លាប​បូក​ព្រលាំង​ដោយ​ជ័រ​ឲ្យ​ក្រាស់​ជិត​សាច់​ពុំ​ឲ្យ​ជ្រាប​ទឹក​បាន : ពរ​ទូក, បិទ​ពរ ។"
    }
  ],
  "synonyms": [],
  "antonyms": [],
  "similar_words": [],
  "sound": null
}
