{
  "word": "យក្ខិនី",
  "type": "kh_kh",
  "definitions": [
    {
      "pos": "",
      "example": "",
      "definition_text": "យក្ខិនីយក្ខិនី   អានថា យ័ក-ខិណី    បា. ឬ សំ.  ( ន. )  ស្រី​យក្ស, យក្ស​ស្រី (ព. កា. ប្រើ​ជា យក្សី ក៏ បាន) ជា អមនុស្ស​ អទិស្សមានកាយ (សូមអានពាក្យ អទិស្សមាន គុ.) ​មាន​ភុម្ម​ទេវតា, វត្ថុ​ទេវតា, អសុរ, បិសាច ជាដើម ពោលគឺជា ពពួកអមនុស្ស ពុំមានខ្លួនអោយគេមើលឃើញ ពិតប្រាកដ។ \nយក្ស យក្សា យក្សី យក្ខ យក្ខីនី \n អានបន្ថែម"
    }
  ],
  "synonyms": [],
  "antonyms": [],
  "similar_words": [],
  "sound": null
}
