{
  "word": "អសង្ហារិមៈ",
  "type": "kh_kh",
  "definitions": [
    {
      "pos": "",
      "example": "",
      "definition_text": "អសង្ហារិមៈអសង្ហារិមៈ   អៈសង់-ហា រិមៈ   បា.  ( គុ. )  (អសំហារិម) ដែល​នាំ​យក ឬ​ដែល​លើក​យក​ទៅ​មក​ពុំ​បាន, ដែល​ពុំ​អាច​ធ្វើ​ឲ្យ​កក្រើក​ឬ​ឲ្យ​ឃ្លាត​ចាក​ទី​បាន : ស្រែ, ចម្ការ, ផ្ទះ​លំនៅ... ជា​អសង្ហារិមៈ ។ ព. ផ្ទ. សង្ហារិមៈ ឬ សំហារិមៈ ។ អសង្ហារិម​ទ្រព្យ ទ្រព្យ​ជា​អសង្ហារិមៈ ។ អសង្ហារិម​ភណ្ឌ ឬ--វត្ថុ ភណ្ឌៈ​ឬ​វត្ថុ​ជា​អសង្ហារិមៈ ។ ល។   អសំហារិមៈ"
    }
  ],
  "synonyms": [],
  "antonyms": [],
  "similar_words": [],
  "sound": null
}
