{
  "word": "អសទិស",
  "type": "kh_kh",
  "definitions": [
    {
      "pos": "",
      "example": "",
      "definition_text": "អសទិសអសទិស   អៈសៈទិសៈ   បា.; សំ.  ( គុ. )  (អសទ្ឫឝ ឬ អសាទ្ឫឝ) ដែល​មិន​ដូច​គ្នា, មិន​ត្រូវ​គ្នា, មិន​ត្រូវ​បែប​គ្នា, មិន​ប្រហែល​គ្នា, មិន​លាំ​គ្នា (ព. ផ្ទ. សទិស, សទិសៈ ឬ សាទិស, សាទិសៈ) ។ បើ​រៀង​ភ្ជាប់​ពី​ខាង​ដើម​សព្ទ​ដទៃ អ. ថ. អៈសៈទិសៈ, អៈសាទិសៈ, ដូច​ជា អសទិស​ន័យ ន័យ​មិន​ដូច​គ្នា ។ អសទិស​ព័ណ៌ ព័ណ៌​ខុស​គ្នា ។ អសទិស​ភាព ភាព​មិន​ដូច​គ្នា ។ អសទិស​សព្ទ សព្ទ​ផ្សេង​គ្នា ។ល។    អសាទិស"
    }
  ],
  "synonyms": [],
  "antonyms": [],
  "similar_words": [],
  "sound": null
}
