{
  "word": "អសង្ខេយ្យ",
  "type": "kh_kh",
  "definitions": [
    {
      "pos": "",
      "example": "",
      "definition_text": "អសង្ខេយ្យអសង្ខេយ្យ   អៈសង់-ខៃ   បា.  ( គុ. )  ដែល​ច្រើន​រាប់​ពុំ​អស់, ដែល​រាប់​ពុំ​បាន​ប្រមាណ​ពុំ​អស់ : ច្រើន​ជា​អសង្ខេយ្យ (ប្រើ​ក្លាយ​ជា អសង្ខៃយ ក៏​មាន) ។ ន. ឈ្មោះ​សំខ្យា​ចំនួន​មួយ​រយ​សែន​មហា​កថាន (មាន ១៤០ សូន្យ) ។ អសង្ខេយ្យ​អប្បមេយ្យ ច្រើន​រាប់​ពុំ​បាន​ស្មាន​ឬ​បៀប​ប្រដូច​ពុំ​កើត... : មាន​ផលានិសង្ស​ជា​អសង្ខេយ្យ​អប្បមេយ្យ ។  \n១០ រយ ស្មើនឹង ១ ពាន់\n១០ ពាន់ ស្មើនឹង ១ ម៉ឺន\n១០ ម៉ឺន ស្មើនឹង ១ សែន\n១០ សែន ស្មើនឹង ១ លាន\n១០ លាន ស្មើនឹង ១ កោដិ\n១០ កោដិ ស្មើនឹង ១ បកោដិ\n១០ បកោដិ ស្មើនឹង ១ កោដិបកោដិ\n១០ កោដិបកោដិ ស្មើនឹង ១ នហុត\n១០ នហុត ស្មើនឹង ១ និន្នហុត\n១០ និន្នហុត ស្មើនឹង ១ អក្ខោភិនី\n១០ អក្ខោភិនី ស្មើនឹង ១ ពិន្ទុ\n១០ ពិន្ទុក ស្មើនឹង ១ អព្វុទៈ\n១០ អព្វុទៈ ស្មើនឹង ១ និរព្វុទៈ\n១០ និរព្វុទៈ ស្មើនឹង ១ អហហៈ\n១០ អហហៈ ស្មើនឹង ១ អដដៈ\n១០ អដដៈ ស្មើនឹង ១ អពពៈ\n១០ អពពៈ ស្មើនឹង ១ សោគន្ធិកៈ\n១០ សោគន្ធិកៈ ស្មើនឹង ១ ឧប្បលៈ\n១០ ឧប្បលៈ ស្មើនឹង ១ កុមុទៈ\n១០ កុមុទៈ ស្មើនឹង ១ បទុមៈ\n១០ បទុមៈ ស្មើនឹង ១ បុណ្ឌរិកៈ\n១០ បុណ្ឌរិកៈ ស្មើនឹង ១ កថានៈ\n១០ កថានៈ ស្មើនឹង ១ មហាកថានៈ\n១០ មហាកថានៈ ស្មើនឹង ១ អសង្ខេយ្យ ។"
    }
  ],
  "synonyms": [],
  "antonyms": [],
  "similar_words": [],
  "sound": null
}
