{
  "word": "accidentally",
  "type": "en_kh",
  "definitions": [
    {
      "pos": "adv",
      "example": "",
      "khmer_image_url": "http://www.english-khmer.com/imgukh/1843.png",
      "local_image_path": "images/1843.png"
    },
    {
      "pos": "adv",
      "example": "",
      "khmer_image_url": "http://www.english-khmer.com/imgukh/131192.png",
      "local_image_path": "images/131192.png"
    }
  ],
  "synonyms": [
    "unintentionally",
    "inadvertently"
  ],
  "antonyms": [],
  "similar_words": [],
  "sound": null,
  "sound_url": "http://www.english-khmer.com/iensound/accidentally.mp3",
  "local_sound_path": "sounds/accidentally.mp3"
}
