{
  "word": "alms",
  "type": "en_kh",
  "definitions": [
    {
      "pos": "n",
      "example": "",
      "khmer_image_url": "http://www.english-khmer.com/imgukh/3587.png",
      "local_image_path": "images/3587.png"
    },
    {
      "pos": "n",
      "example": "",
      "khmer_image_url": "http://www.english-khmer.com/imgukh/112098.png",
      "local_image_path": "images/112098.png"
    }
  ],
  "synonyms": [
    "monies"
  ],
  "antonyms": [],
  "similar_words": [
    "almsgiving",
    "almshouse",
    "almsman"
  ],
  "sound": null,
  "sound_url": "http://www.english-khmer.com/iensound/alms.mp3",
  "local_sound_path": "sounds/alms.mp3"
}
