{
  "word": "arithmetical",
  "type": "en_kh",
  "definitions": [
    {
      "pos": "adj",
      "example": "",
      "khmer_image_url": "http://www.english-khmer.com/imgukh/5481.png",
      "local_image_path": "images/5481.png"
    }
  ],
  "synonyms": [
    "mathematical",
    "numerical",
    "arithmetic",
    "algebraic",
    "statistical"
  ],
  "antonyms": [],
  "similar_words": [],
  "sound": null,
  "sound_url": "http://www.english-khmer.com/iensound/arithmetical.mp3",
  "local_sound_path": "sounds/arithmetical.mp3"
}
