{
  "word": "barmy",
  "type": "en_kh",
  "definitions": [
    {
      "pos": "adj",
      "example": "",
      "khmer_image_url": "http://www.english-khmer.com/imgukh/7518.png",
      "local_image_path": "images/7518.png"
    }
  ],
  "synonyms": [
    "crazy",
    "mad",
    "nuts",
    "silly",
    "foolish",
    "wacky",
    "batty",
    "screwy",
    "cracked",
    "daft",
    "nutty",
    "loopy",
    "loony",
    "crackers",
    "bonkers",
    "potty",
    "irrational"
  ],
  "antonyms": [
    "sensible",
    "sane",
    "rational"
  ],
  "similar_words": [],
  "sound": null,
  "sound_url": "http://www.english-khmer.com/iensound/barmy.mp3",
  "local_sound_path": "sounds/barmy.mp3"
}
