{
  "word": "basophil",
  "type": "en_kh",
  "definitions": [
    {
      "pos": "adj",
      "example": "",
      "khmer_image_url": "http://www.english-khmer.com/imgukh/7665.png",
      "local_image_path": "images/7665.png"
    },
    {
      "pos": "n",
      "example": "",
      "khmer_image_url": "http://www.english-khmer.com/imgukh/7664.png",
      "local_image_path": "images/7664.png"
    }
  ],
  "synonyms": [],
  "antonyms": [],
  "similar_words": [],
  "sound": null,
  "sound_url": "http://www.english-khmer.com/iensound/basophil.mp3",
  "local_sound_path": "sounds/basophil.mp3"
}
