{
  "word": "becripple",
  "type": "en_kh",
  "definitions": [
    {
      "pos": "v",
      "example": "",
      "khmer_image_url": "http://www.english-khmer.com/imgukh/7968.png",
      "local_image_path": "images/7968.png"
    },
    {
      "pos": "v",
      "example": "",
      "khmer_image_url": "http://www.english-khmer.com/imgukh/114789.png",
      "local_image_path": "images/114789.png"
    },
    {
      "pos": "v",
      "example": "",
      "khmer_image_url": "http://www.english-khmer.com/imgukh/114790.png",
      "local_image_path": "images/114790.png"
    }
  ],
  "synonyms": [],
  "antonyms": [],
  "similar_words": [],
  "sound": null,
  "sound_url": "http://www.english-khmer.com/iensound/becripple.mp3",
  "local_sound_path": "sounds/becripple.mp3"
}
