{
  "word": "cheapen",
  "type": "en_kh",
  "definitions": [
    {
      "pos": "tv",
      "example": "",
      "khmer_image_url": "http://www.english-khmer.com/imgukh/13960.png",
      "local_image_path": "images/13960.png"
    }
  ],
  "synonyms": [
    "denigrate",
    "demean",
    "belittle",
    "lower",
    "devalue",
    "depreciate",
    "undervalue",
    "degrade"
  ],
  "antonyms": [
    "elevate"
  ],
  "similar_words": [],
  "sound": null,
  "sound_url": "http://www.english-khmer.com/iensound/cheapen.mp3",
  "local_sound_path": "sounds/cheapen.mp3"
}
