{
  "word": "colonist",
  "type": "en_kh",
  "definitions": [
    {
      "pos": "n",
      "example": "",
      "khmer_image_url": "http://www.english-khmer.com/imgukh/15767.png",
      "local_image_path": "images/15767.png"
    }
  ],
  "synonyms": [
    "migrant",
    "planter",
    "pioneer",
    "immigrant",
    "settler",
    "explorer",
    "colonial",
    "colonizer",
    "conqueror",
    "invader"
  ],
  "antonyms": [
    "native"
  ],
  "similar_words": [],
  "sound": null,
  "sound_url": "http://www.english-khmer.com/iensound/colonist.mp3",
  "local_sound_path": "sounds/colonist.mp3"
}
