{
  "word": "desensitize",
  "type": "en_kh",
  "definitions": [
    {
      "pos": "tv",
      "example": "",
      "khmer_image_url": "http://www.english-khmer.com/imgukh/20820.png",
      "local_image_path": "images/20820.png"
    }
  ],
  "synonyms": [
    "numb",
    "deaden",
    "dull",
    "soothe",
    "pacify",
    "lull"
  ],
  "antonyms": [
    "sensitize"
  ],
  "similar_words": [],
  "sound": null,
  "sound_url": "http://www.english-khmer.com/iensound/desensitize.mp3",
  "local_sound_path": "sounds/desensitize.mp3"
}
