{
  "word": "dialectal",
  "type": "en_kh",
  "definitions": [
    {
      "pos": "adj",
      "example": "",
      "khmer_image_url": "http://www.english-khmer.com/imgukh/21172.png",
      "local_image_path": "images/21172.png"
    },
    {
      "pos": "adj",
      "example": "",
      "khmer_image_url": "http://www.english-khmer.com/imgukh/118253.png",
      "local_image_path": "images/118253.png"
    }
  ],
  "synonyms": [],
  "antonyms": [],
  "similar_words": [],
  "sound": null,
  "sound_url": "http://www.english-khmer.com/iensound/dialectal.mp3",
  "local_sound_path": "sounds/dialectal.mp3"
}
