{
  "word": "directive",
  "type": "en_kh",
  "definitions": [
    {
      "pos": "adj",
      "example": "",
      "khmer_image_url": "http://www.english-khmer.com/imgukh/21510.png",
      "local_image_path": "images/21510.png"
    }
  ],
  "synonyms": [
    "instruction",
    "order",
    "command",
    "dictate",
    "edict",
    "decree",
    "ordinance",
    "ruling",
    "commandment",
    "demand",
    "charge",
    "mandate"
  ],
  "antonyms": [],
  "similar_words": [],
  "sound": null,
  "sound_url": "http://www.english-khmer.com/iensound/directive.mp3",
  "local_sound_path": "sounds/directive.mp3"
}
