{
  "word": "dreamily",
  "type": "en_kh",
  "definitions": [
    {
      "pos": "adv",
      "example": "",
      "khmer_image_url": "http://www.english-khmer.com/imgukh/23082.png",
      "local_image_path": "images/23082.png"
    }
  ],
  "synonyms": [
    "vaguely",
    "distantly",
    "languorously",
    "absentmindedly",
    "abstractedly",
    "pensively"
  ],
  "antonyms": [],
  "similar_words": [],
  "sound": null,
  "sound_url": "http://www.english-khmer.com/iensound/dreamily.mp3",
  "local_sound_path": "sounds/dreamily.mp3"
}
