{
  "word": "encase",
  "type": "en_kh",
  "definitions": [
    {
      "pos": "tv",
      "example": "His broken leg was encased in the plaster.",
      "khmer_image_url": "http://www.english-khmer.com/imgukh/24748.png",
      "local_image_path": "images/24748.png"
    }
  ],
  "synonyms": [
    "cover",
    "enclose",
    "sheath",
    "coat",
    "sheathe",
    "wrap",
    "swathe"
  ],
  "antonyms": [
    "uncover"
  ],
  "similar_words": [],
  "sound": null,
  "sound_url": "http://www.english-khmer.com/iensound/encase.mp3",
  "local_sound_path": "sounds/encase.mp3"
}
