{
  "word": "envoy",
  "type": "en_kh",
  "definitions": [
    {
      "pos": "n",
      "example": "",
      "khmer_image_url": "http://www.english-khmer.com/imgukh/25429.png",
      "local_image_path": "images/25429.png"
    }
  ],
  "synonyms": [
    "representative",
    "emissary",
    "herald",
    "messenger",
    "diplomat",
    "ambassador",
    "legate"
  ],
  "antonyms": [],
  "similar_words": [],
  "sound": null,
  "sound_url": "http://www.english-khmer.com/iensound/envoy.mp3",
  "local_sound_path": "sounds/envoy.mp3"
}
