{
  "word": "grayish",
  "type": "en_kh",
  "definitions": [
    {
      "pos": "adj",
      "example": "",
      "khmer_image_url": "http://www.english-khmer.com/imgukh/32750.png",
      "local_image_path": "images/32750.png"
    }
  ],
  "synonyms": [
    "dirty",
    "discolored",
    "grimy",
    "dull",
    "shadowy",
    "dark",
    "darkish",
    "grey",
    "gray",
    "dim",
    "hazy"
  ],
  "antonyms": [
    "clean",
    "bright"
  ],
  "similar_words": [],
  "sound": null,
  "sound_url": "http://www.english-khmer.com/iensound/grayish.mp3",
  "local_sound_path": "sounds/grayish.mp3"
}
