{
  "word": "idiotic",
  "type": "en_kh",
  "definitions": [
    {
      "pos": "adj",
      "example": "",
      "khmer_image_url": "http://www.english-khmer.com/imgukh/37133.png",
      "local_image_path": "images/37133.png"
    }
  ],
  "synonyms": [
    "foolish",
    "unwise",
    "rash",
    "reckless",
    "foolhardy",
    "silly",
    "daft",
    "senseless",
    "stupid"
  ],
  "antonyms": [
    "wise",
    "sensible"
  ],
  "similar_words": [],
  "sound": null,
  "sound_url": "http://www.english-khmer.com/iensound/idiotic.mp3",
  "local_sound_path": "sounds/idiotic.mp3"
}
