{
  "word": "midair",
  "type": "en_kh",
  "definitions": [
    {
      "pos": "n",
      "example": "",
      "khmer_image_url": "http://www.english-khmer.com/imgukh/108550.png",
      "local_image_path": "images/108550.png"
    }
  ],
  "synonyms": [
    "aerial",
    "airborne",
    "above ground",
    "air",
    "inflight"
  ],
  "antonyms": [],
  "similar_words": [],
  "sound": null,
  "sound_url": "http://www.english-khmer.com/iensound/midair.mp3",
  "local_sound_path": "sounds/midair.mp3"
}
