{
  "word": "slogan",
  "type": "en_kh",
  "definitions": [
    {
      "pos": "n",
      "example": "",
      "khmer_image_url": "http://www.english-khmer.com/imgukh/81353.png",
      "local_image_path": "images/81353.png"
    }
  ],
  "synonyms": [
    "motto",
    "saying",
    "jingle",
    "refrain"
  ],
  "antonyms": [],
  "similar_words": [
    "sloganize",
    "sloganizer"
  ],
  "sound": null,
  "sound_url": "http://www.english-khmer.com/iensound/slogan.mp3",
  "local_sound_path": "sounds/slogan.mp3"
}
