{
  "word": "spiritual",
  "type": "en_kh",
  "definitions": [
    {
      "pos": "adj",
      "example": "spiritual experience",
      "khmer_image_url": "http://www.english-khmer.com/imgukh/83450.png",
      "local_image_path": "images/83450.png"
    },
    {
      "pos": "adj",
      "example": "spiritual health",
      "khmer_image_url": "http://www.english-khmer.com/imgukh/83451.png",
      "local_image_path": "images/83451.png"
    },
    {
      "pos": "adj",
      "example": "spiritual phenomena",
      "khmer_image_url": "http://www.english-khmer.com/imgukh/83452.png",
      "local_image_path": "images/83452.png"
    },
    {
      "pos": "n",
      "example": "",
      "khmer_image_url": "http://www.english-khmer.com/imgukh/83453.png",
      "local_image_path": "images/83453.png"
    }
  ],
  "synonyms": [
    "divine",
    "unworldly",
    "psychic",
    "religious",
    "holy",
    "saintly",
    "pious",
    "sacred",
    "devout",
    "heavenly"
  ],
  "antonyms": [
    "secular",
    "physical"
  ],
  "similar_words": [
    "spiritual leader",
    "spiritual mind",
    "spiritual-mindedness",
    "spiritualism",
    "spiritualist",
    "spiritualistic",
    "spirituality",
    "spiritualize"
  ],
  "sound": null,
  "sound_url": "http://www.english-khmer.com/iensound/spiritual.mp3",
  "local_sound_path": "sounds/spiritual.mp3"
}
