{
  "word": "termination",
  "type": "en_kh",
  "definitions": [
    {
      "pos": "n",
      "example": "",
      "khmer_image_url": "http://www.english-khmer.com/imgukh/88367.png",
      "local_image_path": "images/88367.png"
    },
    {
      "pos": "n",
      "example": "",
      "khmer_image_url": "http://www.english-khmer.com/imgukh/88368.png",
      "local_image_path": "images/88368.png"
    },
    {
      "pos": "n",
      "example": "",
      "khmer_image_url": "http://www.english-khmer.com/imgukh/128158.png",
      "local_image_path": "images/128158.png"
    },
    {
      "pos": "n",
      "example": "",
      "khmer_image_url": "http://www.english-khmer.com/imgukh/128159.png",
      "local_image_path": "images/128159.png"
    },
    {
      "pos": "n",
      "example": "",
      "khmer_image_url": "http://www.english-khmer.com/imgukh/128160.png",
      "local_image_path": "images/128160.png"
    }
  ],
  "synonyms": [
    "extinction",
    "annihilation",
    "execution",
    "killing",
    "slaughter",
    "massacre",
    "butchery",
    "close",
    "standstill",
    "break",
    "pause",
    "cessation",
    "stop"
  ],
  "antonyms": [
    "preservation",
    "start"
  ],
  "similar_words": [],
  "sound": null,
  "sound_url": "http://www.english-khmer.com/iensound/termination.mp3",
  "local_sound_path": "sounds/termination.mp3"
}
