{
  "word": "unblock",
  "type": "en_kh",
  "definitions": [
    {
      "pos": "tv",
      "example": "",
      "khmer_image_url": "http://www.english-khmer.com/imgukh/93410.png",
      "local_image_path": "images/93410.png"
    }
  ],
  "synonyms": [
    "unclog",
    "clear",
    "free",
    "release",
    "clean"
  ],
  "antonyms": [
    "block"
  ],
  "similar_words": [],
  "sound": null,
  "sound_url": "http://www.english-khmer.com/iensound/unblock.mp3",
  "local_sound_path": "sounds/unblock.mp3"
}
