{
  "word": "unimaginative",
  "type": "en_kh",
  "definitions": [
    {
      "pos": "adj",
      "example": "",
      "khmer_image_url": "http://www.english-khmer.com/imgukh/94543.png",
      "local_image_path": "images/94543.png"
    }
  ],
  "synonyms": [
    "dull",
    "boring",
    "insipid",
    "bland",
    "uninspired",
    "unoriginal",
    "derivative",
    "lackluster",
    "unexciting",
    "featureless",
    "mundane",
    "ordinary",
    "routine"
  ],
  "antonyms": [
    "imaginative"
  ],
  "similar_words": [],
  "sound": null,
  "sound_url": "http://www.english-khmer.com/iensound/unimaginative.mp3",
  "local_sound_path": "sounds/unimaginative.mp3"
}
