{
  "word": "unwillingness",
  "type": "en_kh",
  "definitions": [
    {
      "pos": "n",
      "example": "",
      "khmer_image_url": "http://www.english-khmer.com/imgukh/96616.png",
      "local_image_path": "images/96616.png"
    }
  ],
  "synonyms": [
    "reluctance",
    "disinclination",
    "refusal",
    "indisposition",
    "aversion",
    "opposition"
  ],
  "antonyms": [
    "inclination",
    "willingness"
  ],
  "similar_words": [],
  "sound": null,
  "sound_url": "http://www.english-khmer.com/iensound/unwillingness.mp3",
  "local_sound_path": "sounds/unwillingness.mp3"
}
